mockernetes/__init__.py
mockernetes/mock.py
mockernetes/mock_apis.py
mockernetes/mock_client.py
mockernetes-0.1.0.dist-info/METADATA
mockernetes-0.1.0.dist-info/WHEEL
mockernetes-0.1.0.dist-info/entry_points.txt
mockernetes-0.1.0.dist-info/RECORD
