Metadata-Version: 2.4
Name: mockernetes
Version: 0.1.0
Summary: A moto-like library for mocking Kubernetes API in Python tests with stateful in-memory behavior
Project-URL: Repository, https://github.com/tofarr/mockernetes
Requires-Python: >=3.12
Requires-Dist: kubernetes>=34.1.0
Requires-Dist: pytest>=9.0.2
Provides-Extra: dev
Requires-Dist: black>=23.3; extra == 'dev'
Requires-Dist: pylint>=3.0; extra == 'dev'
Requires-Dist: pytest-cov>=4.0; extra == 'dev'
Requires-Dist: pytest-xdist>=3.2; extra == 'dev'
